{"brewery":"yamane","_note":"副原料の茶は公式『飯能産茶葉』だがSAKE Street記事は『狭山茶』表記の揺れあり。ABVはロットで9〜14度と大きく変動","brands":{"やまねのみのり（茶Ver.）":{"abv":null,"volume_ml":300,"price":1500,"price_note":"税込(2022/10発売・直売/BASE)。Makuake版『宮沢の誉』は300ml3,000円の別ロット","sub_ingredients_detail":"飯能産茶葉(公式『飯能で収穫』)。Makuake版は飯能たなべ園『宮沢の誉』","rice_variety":"埼玉県産米(Makuake版は熊谷百歳農園の自然栽培陸羽132号)","rice_polish":null,"shubo":null,"koji":"米麹","yeast":"協会6号酵母(新政酵母)","water":null,"vessel":"木桶(飯能産西川材の道具。Makuake版は小豆島坂口工務店の新木桶150L)","pasteurized":false,"draft":null,"serving_temp":null,"glass":null,"preservation":"生酒のため要冷蔵。直射日光で茶成分により赤く変色","pairing":null,"tasting_nose":null,"tasting_palate":null,"tasting_finish":null,"tasting_source_name":null,"tasting_source_url":null,"story":"米・米麹・水に飯能産茶葉を加え全量袋吊りで搾ったクラフトサケ。生物研究家でもある代表・若林福成。売上一部を飯能の自然保全に充当。道具に飯能産西川材","story_source_url":"https://yamaneshuzo.jp/","awards":[],"flavor_basis":"全量袋吊り・薄濁り・木桶。茶Ver固有の定量フレーバーは非公開。協会6号"},"やまねのみのり（蜂蜜Ver.）":{"abv":null,"volume_ml":300,"price":1500,"price_note":"税込(2022/10発売)","sub_ingredients_detail":"飯能産蜂蜜(公式『飯能含む周辺で採蜜』)","rice_variety":"埼玉県産米","rice_polish":null,"shubo":null,"koji":"米麹","yeast":"協会6号酵母(新政酵母)","water":null,"vessel":"木桶(飯能産西川材)","pasteurized":null,"draft":null,"serving_temp":null,"glass":null,"preservation":null,"pairing":null,"tasting_nose":null,"tasting_palate":null,"tasting_finish":null,"tasting_source_name":null,"tasting_source_url":null,"story":"米・米麹・水に飯能含む周辺で採蜜した蜂蜜を加え全量袋吊りで搾ったクラフトサケ","story_source_url":"https://yamaneshuzo.jp/","awards":[],"flavor_basis":"全量袋吊り・木桶・蜂蜜由来。蜂蜜Ver固有のテイスティングは非公開。協会6号"},"やまねのみのり（発芽玄米Ver.）":{"abv":null,"volume_ml":null,"price":null,"price_note":"標準品の公式定価は未確認。ロットで度数9〜14度変動。1.8L生酒の流通あり","sub_ingredients_detail":"発芽玄米。SAKE Street記事では『9割以上発芽玄米ごく微量、残りは飯能産茶葉(狭山茶)』","rice_variety":"埼玉県産米","rice_polish":null,"shubo":null,"koji":"米麹","yeast":"協会6号酵母(新政酵母)","water":null,"vessel":"木桶(飯能産西川材)","pasteurized":false,"draft":true,"serving_temp":"冷酒〜常温(温度上げると木桶の味わいと甘み増)","glass":null,"preservation":"生酒・発酵継続のため要冷蔵。ガス抜き小穴キャップ","pairing":null,"tasting_nose":"酸味を感じさせるパイナップル様の香り(二次情報)","tasting_palate":"力強い酸味とさっぱり甘み旨味、苦みで複雑味(14度ロット)。微発泡","tasting_finish":"スッキリ","tasting_source_name":"yamaro.info(個人レビュー・二次情報)","tasting_source_url":"https://yamaro.info/wordpress/2025/08/01/","story":"米・米麹・水に発芽玄米を加えたクラフトサケ。木桶仕込み・全量袋吊り。生き物がつくる個性を信じた酒造り","story_source_url":"https://sakestreet.com/ja/media/sakagura-yamane-shuzo-saitama","awards":[],"flavor_basis":"薄濁り〜にごり・微発泡・木桶。酸味前面+甘味旨味苦味の複雑味。ボディは温度で増す。二次情報"}},"confidence_notes":"公式site/BASE/Makuake中心。茶蜂蜜は300ml1500円・全量袋吊り・協会6号・木桶確定。ABVはロット変動で固定値なしnull。精米歩合・酒母・仕込水は非公開。テイスティングは発芽玄米のみ二次情報。茶呼称は飯能産茶葉/狭山茶の揺れ。受賞なし。"}
